unvcode/NotoSerifSC-SemiBold.otf
unvcode/__init__.py
unvcode-1.0.0.dist-info/METADATA
unvcode-1.0.0.dist-info/WHEEL
unvcode-1.0.0.dist-info/top_level.txt
unvcode-1.0.0.dist-info/RECORD
