Metadata-Version: 2.1
Name: unvcode
Version: 1.0.0
Summary: unvcode
Home-page: https://github.com/RimoChan/unvcode
Author: RimoChan
Author-email: the@librian.net
License: UNKNOWN
Platform: UNKNOWN
Classifier: Programming Language :: Python :: 3
Classifier: Operating System :: OS Independent
Requires-Python: >=3.6
Requires-Dist: numpy (>=1.16.6)
Requires-Dist: Pillow (>=8.0.1)
